langchain_hana/__init__.py
langchain_hana/chains/__init__.py
langchain_hana/chains/graph_qa/__init__.py
langchain_hana/chains/graph_qa/prompts.py
langchain_hana/chains/graph_qa/sparql_qa_chain.py
langchain_hana/embeddings.py
langchain_hana/graphs/__init__.py
langchain_hana/graphs/hana_rdf_graph.py
langchain_hana/py.typed
langchain_hana/query_constructors.py
langchain_hana/utils.py
langchain_hana/vectorstores.py
langchain_hana-0.2.3.dist-info/LICENSE
langchain_hana-0.2.3.dist-info/LICENSES/Apache-2.0.txt
langchain_hana-0.2.3.dist-info/METADATA
langchain_hana-0.2.3.dist-info/WHEEL
langchain_hana-0.2.3.dist-info/RECORD
